twtoolbox/__init__.py
twtoolbox/cli.py
twtoolbox/defaults.cfg
twtoolbox/helpers.py
twtoolbox/streaming.py
twtoolbox/tweets.py
twtoolbox/users.py
twitter_toolbox-1.2.4.dist-info/LICENSE
twitter_toolbox-1.2.4.dist-info/METADATA
twitter_toolbox-1.2.4.dist-info/WHEEL
twitter_toolbox-1.2.4.dist-info/entry_points.txt
twitter_toolbox-1.2.4.dist-info/top_level.txt
twitter_toolbox-1.2.4.dist-info/RECORD
