Metadata-Version: 2.1
Name: twitter-toolbox
Version: 1.2.4
Summary: Twitter Toolbox for Python
Home-page: https://github.com/hhromic/python-twitter-toolbox
Author: Hugo Hromic
Author-email: hhromic@gmail.com
Maintainer: Hugo Hromic
Maintainer-email: hhromic@gmail.com
License: Apache-2.0
Download-URL: https://github.com/hhromic/python-twitter-toolbox/tarball/1.2.4
Keywords: twitter,api,cli,toolbox
Platform: all
Classifier: Environment :: Console
Requires: tweepy
Requires: colorlog
Provides: twtoolbox
Requires-Dist: tweepy
Requires-Dist: colorlog
